pyppeteer_ghost_cursor/__init__.py
pyppeteer_ghost_cursor/math.py
pyppeteer_ghost_cursor/mouseHelper.py
pyppeteer_ghost_cursor/spoof.py
pyppeteer_ghost_cursor/js/mouseHelper.js
python_ghost_cursor/__init__.py
python_ghost_cursor/js/mouseHelper.js
python_ghost_cursor/playwright_async/__init__.py
python_ghost_cursor/playwright_async/_mouse_helper.py
python_ghost_cursor/playwright_async/_spoof.py
python_ghost_cursor/playwright_sync/__init__.py
python_ghost_cursor/playwright_sync/_mouse_helper.py
python_ghost_cursor/playwright_sync/_spoof.py
python_ghost_cursor/pyppeteer/__init__.py
python_ghost_cursor/pyppeteer/_mouse_helper.py
python_ghost_cursor/pyppeteer/_spoof.py
python_ghost_cursor/shared/__init__.py
python_ghost_cursor/shared/_math.py
python_ghost_cursor/shared/_spoof.py
python_ghost_cursor-0.1.1.dist-info/LICENSE
python_ghost_cursor-0.1.1.dist-info/METADATA
python_ghost_cursor-0.1.1.dist-info/WHEEL
python_ghost_cursor-0.1.1.dist-info/top_level.txt
python_ghost_cursor-0.1.1.dist-info/RECORD
