Metadata-Version: 2.1
Name: python-ghost-cursor
Version: 0.1.1
Summary: Python implementation of Xetera/ghost-cursor
Home-page: https://github.com/mcolella14/python_ghost_cursor
Author: mcolella14
Author-email: mcolella14@gmail.com
License: MIT
Platform: UNKNOWN
Classifier: Topic :: Software Development :: Testing
Classifier: Topic :: Internet :: WWW/HTTP :: Browsers
Classifier: Intended Audience :: Developers
Classifier: Programming Language :: Python :: 3
Classifier: Programming Language :: Python :: 3.7
Classifier: Programming Language :: Python :: 3.8
Classifier: Programming Language :: Python :: 3.9
Classifier: License :: OSI Approved :: MIT License
Classifier: Operating System :: OS Independent
